cascade/__init__.py
cascade/TSO/TSO.py
cascade/TSO/__init__.py
cascade/build_archive/__init__.py
cascade/build_archive/build_archive.py
cascade/cpm_model/__init__.py
cascade/cpm_model/cpm_model.py
cascade/data_model/__init__.py
cascade/data_model/data_model.py
cascade/exoplanet_tools/__init__.py
cascade/exoplanet_tools/exoplanet_tools.py
cascade/initialize/__init__.py
cascade/initialize/initialize.py
cascade/instruments/InstrumentsBaseClasses.py
cascade/instruments/ObservationGenerator.py
cascade/instruments/__init__.py
cascade/instruments/Generic/Generic.py
cascade/instruments/Generic/__init__.py
cascade/instruments/HST/HST.py
cascade/instruments/HST/__init__.py
cascade/instruments/JWST/JWST.py
cascade/instruments/JWST/__init__.py
cascade/instruments/Spitzer/Spitzer.py
cascade/instruments/Spitzer/__init__.py
cascade/spectral_extraction/__init__.py
cascade/spectral_extraction/spectral_extraction.py
cascade/utilities/__init__.py
cascade/utilities/readwrite_spectra.py
cascade/utilities/utilities.py
cascade/verbose/__init__.py
cascade/verbose/verbose.py
cascade_spectroscopy-1.2.14.data/data/LICENSE.txt
cascade_spectroscopy-1.2.14.data/data/README.md
cascade_spectroscopy-1.2.14.data/scripts/build_local_hst_archive.py
cascade_spectroscopy-1.2.14.data/scripts/run_cascade.py
cascade_spectroscopy-1.2.14.data/scripts/run_cascade.sh
cascade_spectroscopy-1.2.14.data/scripts/run_stats.sh
cascade_spectroscopy-1.2.14.data/scripts/setup_cascade.py
cascade_spectroscopy-1.2.14.dist-info/licenses/LICENSE.txt
tests/__init__.py
tests/cascade_tests.py
tests/cpm_model_tests.py
tests/data_model_tests.py
tests/exoplanet_tools_tests.py
tests/initialize_tests.py
cascade_spectroscopy-1.2.14.dist-info/METADATA
cascade_spectroscopy-1.2.14.dist-info/WHEEL
cascade_spectroscopy-1.2.14.dist-info/top_level.txt
cascade_spectroscopy-1.2.14.dist-info/RECORD
