Metadata-Version: 2.4
Name: CASCADe-spectroscopy
Version: 1.2.14
Summary: CASCADe : Calibration of trAnsit Spectroscopy using CAusal Data
Home-page: https://jbouwman.gitlab.io/CASCADe/
Download-URL: https://gitlab.com/jbouwman/CASCADe
Author: Jeroen Bouwman
Author-email: bouwman@mpia.de
License: GNU General Public License v3 (GPLv3)
Classifier: Programming Language :: Python :: 3
Classifier: License :: OSI Approved :: GNU General Public License v3 (GPLv3)
Classifier: Operating System :: OS Independent
Classifier: Intended Audience :: Science/Research
Classifier: Topic :: Scientific/Engineering :: Astronomy
Requires-Python: >=3.10, <3.13
License-File: LICENSE.txt
Requires-Dist: batman-package
Requires-Dist: astropy
Requires-Dist: jplephem
Requires-Dist: scipy
Requires-Dist: numpy
Requires-Dist: configparser
Requires-Dist: photutils
Requires-Dist: pandas
Requires-Dist: scikit-learn
Requires-Dist: matplotlib
Requires-Dist: tqdm
Requires-Dist: seaborn
Requires-Dist: pytest
Requires-Dist: scikit-image>=0.22
Requires-Dist: sphinx
Requires-Dist: alabaster
Requires-Dist: networkx
Requires-Dist: cython
Requires-Dist: astroquery
Requires-Dist: numba
Requires-Dist: ray[default]
Requires-Dist: pyfiglet
Requires-Dist: termcolor
Requires-Dist: statsmodels
Requires-Dist: h5py
Requires-Dist: exotethys
Requires-Dist: jupyter
Requires-Dist: ipython
Requires-Dist: jwst
Dynamic: author
Dynamic: author-email
Dynamic: classifier
Dynamic: description
Dynamic: description-content-type
Dynamic: download-url
Dynamic: home-page
Dynamic: license
Dynamic: license-file
Dynamic: requires-dist
Dynamic: requires-python
Dynamic: summary
